httplib2shim/__init__.py
httplib2shim/test/__init__.py
httplib2shim/test/httplib2_test.py
httplib2shim-0.0.2.dist-info/DESCRIPTION.rst
httplib2shim-0.0.2.dist-info/METADATA
httplib2shim-0.0.2.dist-info/RECORD
httplib2shim-0.0.2.dist-info/WHEEL
httplib2shim-0.0.2.dist-info/metadata.json
httplib2shim-0.0.2.dist-info/top_level.txt
