Metadata-Version: 2.0
Name: httplib2shim
Version: 0.0.2
Summary: A wrapper over urllib3 that matches httplib2's interface
Home-page: https://github.com/GoogleCloudPlatform/httplib2shim
Author: Jon Wayne Parrott
Author-email: jonwayne@google.com
License: MIT
Keywords: httplib2 http urllib3
Platform: UNKNOWN
Classifier: Development Status :: 3 - Alpha
Classifier: Intended Audience :: Developers
Classifier: Topic :: Software Development :: Libraries :: Python Modules
Classifier: Topic :: Internet
Classifier: License :: OSI Approved :: Apache Software License
Classifier: Programming Language :: Python
Classifier: Programming Language :: Python :: 2
Classifier: Programming Language :: Python :: 3
Classifier: Programming Language :: Python :: 2.7
Classifier: Programming Language :: Python :: 3.4
Classifier: Operating System :: POSIX
Classifier: Operating System :: MacOS
Classifier: Operating System :: Unix
Requires-Dist: certifi
Requires-Dist: httplib2
Requires-Dist: six
Requires-Dist: urllib3
